<?xml version = '1.0' encoding = 'UTF-8'?>
<Relation class="oracle.dbtools.crest.model.design.logical.Relation" name="F15E4comm_F15E4RFE_FK" directorySegmentName="seg_0" id="60131F5E-2A3E-BEA4-BDEC-8117769F1826">
<createdBy>Mark1</createdBy>
<createdTime>2015-11-11 00:03:12 UTC</createdTime>
<generatorID>315A1AF6-38AF-53A3-1987-4A334417C585</generatorID>
<ownerDesignName>new_logical</ownerDesignName>
<engineerTo>
<item key="C124704E-CE6D-D1AB-1EA8-03085175F32E" value="true"/>
</engineerTo>
<sourcePk>108F2F12-3AD9-1E35-4A9A-24014806774C</sourcePk>
<identifying>false</identifying>
<optionalSource>true</optionalSource>
<optionalTarget>true</optionalTarget>
<sourceCardinality>1</sourceCardinality>
<sourceEntity>21EF4E99-E490-5A19-874F-10CFF8F320F9</sourceEntity>
<targetCardinalityString>*</targetCardinalityString>
<targetEntity>4889AAB0-2162-AD1B-86FB-392176F39846</targetEntity>
<transferable>true</transferable>
<deleteRule>NO ACTION</deleteRule>
</Relation>