<?xml version = '1.0' encoding = 'UTF-8'?>
<Relation class="oracle.dbtools.crest.model.design.logical.Relation" name="Relation_10" directorySegmentName="seg_0" id="C5B51E53-D4AB-C295-FB32-48E050974F94">
<createdBy>Mark1</createdBy>
<createdTime>2015-10-19 21:56:17 UTC</createdTime>
<ownerDesignName>conceptual1</ownerDesignName>
<engineerTo>
<item key="419FF07C-E508-E581-9CBB-3112C4B77996" value="true"/>
</engineerTo>
<sourcePk>BE16CFE7-7417-A71C-A21F-A2A8C52F14D1</sourcePk>
<identifying>false</identifying>
<optionalSource>true</optionalSource>
<optionalTarget>true</optionalTarget>
<sourceCardinality>1</sourceCardinality>
<sourceEntity>CD17C6BE-F4B3-1753-57B6-B9020DC7D26C</sourceEntity>
<targetCardinalityString>*</targetCardinalityString>
<targetEntity>0749EBDE-BFB8-A085-97AF-4F0063CE9EEB</targetEntity>
<transferable>true</transferable>
<deleteRule>NO ACTION</deleteRule>
</Relation>